odoo9_addon_pricelist_per_product-9.0.1.0.0.99.dev8-nspkg.pth
odoo_addons/pricelist_per_product/README.rst
odoo_addons/pricelist_per_product/__init__.py
odoo_addons/pricelist_per_product/__openerp__.py
odoo_addons/pricelist_per_product/i18n/es.po
odoo_addons/pricelist_per_product/i18n/pricelist_per_product.pot
odoo_addons/pricelist_per_product/models/__init__.py
odoo_addons/pricelist_per_product/models/product_pricelist.py
odoo_addons/pricelist_per_product/models/product_pricelist_item.py
odoo_addons/pricelist_per_product/static/description/icon.png
odoo_addons/pricelist_per_product/tests/__init__.py
odoo_addons/pricelist_per_product/tests/test_product_pricelist.py
odoo_addons/pricelist_per_product/tests/test_product_pricelist_item.py
odoo_addons/pricelist_per_product/views/product_pricelist_item_view.xml
odoo_addons/pricelist_per_product/views/product_pricelist_view.xml
odoo_addons/pricelist_per_product/views/product_template_view.xml
odoo9_addon_pricelist_per_product-9.0.1.0.0.99.dev8.dist-info/METADATA
odoo9_addon_pricelist_per_product-9.0.1.0.0.99.dev8.dist-info/WHEEL
odoo9_addon_pricelist_per_product-9.0.1.0.0.99.dev8.dist-info/namespace_packages.txt
odoo9_addon_pricelist_per_product-9.0.1.0.0.99.dev8.dist-info/top_level.txt
odoo9_addon_pricelist_per_product-9.0.1.0.0.99.dev8.dist-info/RECORD
